pastebin_bisque/__init__.py
pastebin_bisque/__main__.py
pastebin_bisque/cli.py
pastebin_bisque/tests/__init__.py
pastebin_bisque-1.0.0.dist-info/AUTHORS.rst
pastebin_bisque-1.0.0.dist-info/LICENSE
pastebin_bisque-1.0.0.dist-info/METADATA
pastebin_bisque-1.0.0.dist-info/WHEEL
pastebin_bisque-1.0.0.dist-info/entry_points.txt
pastebin_bisque-1.0.0.dist-info/top_level.txt
pastebin_bisque-1.0.0.dist-info/RECORD
