Metadata-Version: 2.1
Name: pastebin-bisque
Version: 1.0.0
Summary: Scrape all public Pastebin pastes from a user.
Home-page: https://github.com/bbbbbrie/pastebin-bisque
Author: Brie Carranza
Author-email: hi@brie.ninja
License: LGPL-3.0-or-later
Project-URL: 📝 Documentation, https://pastebin-bisque.readthedocs.io/
Project-URL: 🚀 Changelog, https://pastebin-bisque.readthedocs.io/en/latest/changelog.html
Project-URL: 💡 Issue Tracker, https://github.com/bbbbbrie/pastebin-bisque/issues
Keywords: pastebin,osint,security,research,scraping
Classifier: Development Status :: 5 - Production/Stable
Classifier: Intended Audience :: Developers
Classifier: License :: OSI Approved :: GNU Lesser General Public License v3 or later (LGPLv3+)
Classifier: Operating System :: Unix
Classifier: Operating System :: POSIX
Classifier: Operating System :: Microsoft :: Windows
Classifier: Programming Language :: Python
Classifier: Programming Language :: Python :: 3
Classifier: Programming Language :: Python :: 3 :: Only
Classifier: Programming Language :: Python :: 3.7
Classifier: Programming Language :: Python :: 3.8
Classifier: Programming Language :: Python :: 3.9
Classifier: Programming Language :: Python :: 3.10
Classifier: Programming Language :: Python :: 3.11
Classifier: Programming Language :: Python :: Implementation :: CPython
Classifier: Programming Language :: Python :: Implementation :: PyPy
Classifier: Topic :: Utilities
Requires-Python: >=3.7
License-File: LICENSE
License-File: AUTHORS.rst
Requires-Dist: loguru ==0.7.1
Requires-Dist: beautifulsoup4 ==4.12.2
Requires-Dist: certifi ==2023.7.22
Requires-Dist: chardet ==5.2.0
Requires-Dist: charset-normalizer ==3.2.0
Requires-Dist: Click ==8.1.7
Requires-Dist: idna ==3.4
Requires-Dist: pathvalidate ==3.1.0
Requires-Dist: requests ==2.31.0
Requires-Dist: six ==1.16.0
Requires-Dist: soupsieve ==2.5
Requires-Dist: urllib3 ==2.0.4
